relari_otel/.DS_Store
relari_otel/__init__.py
relari_otel/otel.py
relari_otel/semcov.py
relari_otel/specifications/__init__.py
relari_otel/specifications/contract.py
relari_otel/specifications/requirements.py
relari_otel/specifications/specifications.py
relari_otel/tracing.py
relari_otel/utils.py
relari_otel-0.0.1.dist-info/LICENSE
relari_otel-0.0.1.dist-info/METADATA
relari_otel-0.0.1.dist-info/WHEEL
relari_otel-0.0.1.dist-info/RECORD
