Metadata-Version: 2.1
Name: relari-otel
Version: 0.0.1
Summary: Relari Open-Telemetry package
License: Apache-2.0
Author: Pasquale Antonante
Author-email: pasquale@relari.ai
Requires-Python: >=3.9,<3.14
Classifier: License :: OSI Approved :: Apache Software License
Classifier: Programming Language :: Python :: 3
Classifier: Programming Language :: Python :: 3.9
Classifier: Programming Language :: Python :: 3.10
Classifier: Programming Language :: Python :: 3.11
Classifier: Programming Language :: Python :: 3.12
Provides-Extra: certification
Provides-Extra: langchain
Provides-Extra: openai
Requires-Dist: openinference-instrumentation-langchain (>=0.1.35,<0.2.0) ; extra == "langchain"
Requires-Dist: openinference-instrumentation-openai (>=0.1.21,<0.2.0) ; extra == "openai"
Requires-Dist: openinference-semantic-conventions (>=0.1.14,<0.2.0)
Requires-Dist: opentelemetry-exporter-otlp-proto-http (>=1.30.0,<2.0.0)
Requires-Dist: opentelemetry-sdk (>=1.30.0,<2.0.0)
Requires-Dist: redis (>=5.2.1,<6.0.0) ; extra == "certification"
